atomcalc/__init__.py
atomcalc/Decay.py
atomcalc/Laser.py
atomcalc/Level.py
atomcalc/plot_pulse.py
atomcalc/System.py
atomcalc-0.1.7.dist-info/METADATA
atomcalc-0.1.7.dist-info/WHEEL
atomcalc-0.1.7.dist-info/RECORD
