Metadata-Version: 2.1
Name: atomcalc
Version: 0.1.7
Summary: 
Author: Moritz Wilke
Requires-Python: >=3.8.5,<3.12
Classifier: Programming Language :: Python :: 3
Classifier: Programming Language :: Python :: 3.9
Classifier: Programming Language :: Python :: 3.10
Classifier: Programming Language :: Python :: 3.11
Requires-Dist: matplotlib (>=3.7.1,<4.0.0)
Requires-Dist: numpy (>=1.24.3,<2.0.0)
Requires-Dist: qutip (>=4.7.1,<5.0.0)
Requires-Dist: scipy (==1.10.1)
Project-URL: homepage, https://atomcalc.github.io/AtomCalc/
